CHANGES.txt
LICENSE.txt
MANIFEST
MANIFEST.in
README.txt
setup.py
ControlMyPi.egg-info/PKG-INFO
ControlMyPi.egg-info/SOURCES.txt
ControlMyPi.egg-info/dependency_links.txt
ControlMyPi.egg-info/requires.txt
ControlMyPi.egg-info/top_level.txt
controlmypi/__init__.py