Metadata-Version: 1.0
Name: ControlMyPi
Version: 0.1.3
Summary: Client library for ControlMyPi scripts.
Home-page: http://www.controlmypi.com/
Author: Jeremy Blythe
Author-email: jerbly@controlmypi.com
License: LICENSE.txt
Platform: UNKNOWN
